[null,{"name":"Status","temp":"","event-type":"1","actions":[{"gameName":"I'm Yoshino, Neet's Sister","gameLink":"","name":"Set Bot Game"},{"status":"0","name":"Set Bot Status"}]},{"name":"Emoji","temp":"emo","event-type":"16","actions":[{"info":"1","find":"changes","storage":"1","varName":"channel","name":"Find Channel"},{"channel":"5","varName":"channel","message":"An emoji was created!\n${tempVars(\"emo\")}","storage":"0","varName2":"","name":"Send Message"}]},{"name":"Channel","temp":"channel","event-type":"8","actions":[{"info":"1","find":"changes","storage":"1","varName":"channel2","name":"Find Channel"},{"channel":"3","varName":"channel","info":"2","storage":"1","varName2":"name","name":"Store Channel Info"},{"channel":"5","varName":"channel2","message":"A channel called ***${tempVars(\"name\")}***  was created!","storage":"0","varName2":"","name":"Send Message"}]}]